pgprovision/__init__.py
pgprovision/cli.py
pgprovision/_sh/__init__.py
pgprovision/_sh/provision.sh
pgprovision/_sh/lib/common.sh
pgprovision/_sh/lib/hba.sh
pgprovision/_sh/lib/profile.sh
pgprovision/_sh/os/rhel.sh
pgprovision/_sh/os/ubuntu.sh
pgprovision/_sh/profiles/xl-32c-256g.conf
pg_provision-0.2.5.dist-info/LICENSE
pg_provision-0.2.5.dist-info/METADATA
pg_provision-0.2.5.dist-info/WHEEL
pg_provision-0.2.5.dist-info/entry_points.txt
pg_provision-0.2.5.dist-info/top_level.txt
pg_provision-0.2.5.dist-info/RECORD
