Metadata-Version: 2.2
Name: pg-provision
Version: 0.2.5
Summary: Idempotent PostgreSQL provisioning as a Python package (wrapping portable shell scripts)
Author-email: John Jenkins <scr1ptcat@protonmail.com>
License: MIT
Project-URL: Homepage, https://github.com/scr1ptcat/pg-provision
Project-URL: Repository, https://github.com/scr1ptcat/pg-provision
Project-URL: Issues, https://github.com/scr1ptcat/pg-provision/issues
Project-URL: PyPI, https://pypi.org/project/pg-provision/
Classifier: Programming Language :: Python :: 3
Classifier: Programming Language :: Python :: 3.9
Classifier: Programming Language :: Python :: 3.10
Classifier: Programming Language :: Python :: 3.11
Classifier: Programming Language :: Python :: 3.12
Classifier: Programming Language :: Python :: 3.13
Classifier: Environment :: Console
Classifier: Topic :: System :: Systems Administration
Classifier: License :: OSI Approved :: MIT License
Classifier: Programming Language :: Python :: 3 :: Only
Classifier: Operating System :: POSIX :: Linux
Classifier: Intended Audience :: System Administrators
Requires-Python: >=3.9
License-File: LICENSE
